roampal/__init__.py
roampal/__main__.py
roampal/cli.py
roampal/backend/__init__.py
roampal/backend/modules/__init__.py
roampal/backend/modules/memory/__init__.py
roampal/backend/modules/memory/chromadb_adapter.py
roampal/backend/modules/memory/config.py
roampal/backend/modules/memory/content_graph.py
roampal/backend/modules/memory/context_service.py
roampal/backend/modules/memory/embedding_service.py
roampal/backend/modules/memory/knowledge_graph_service.py
roampal/backend/modules/memory/memory_bank_service.py
roampal/backend/modules/memory/memory_types.py
roampal/backend/modules/memory/outcome_service.py
roampal/backend/modules/memory/promotion_service.py
roampal/backend/modules/memory/routing_service.py
roampal/backend/modules/memory/scoring_service.py
roampal/backend/modules/memory/search_service.py
roampal/backend/modules/memory/unified_memory_system.py
roampal/backend/modules/memory/tests/__init__.py
roampal/backend/modules/memory/tests/conftest.py
roampal/backend/modules/memory/tests/pii_guard_config.example.py
roampal/backend/modules/memory/tests/pii_guard_config.py
roampal/backend/modules/memory/tests/integration/__init__.py
roampal/backend/modules/memory/tests/integration/test_action_kg_sync.py
roampal/backend/modules/memory/tests/integration/test_chromadb_integration.py
roampal/backend/modules/memory/tests/unit/__init__.py
roampal/backend/modules/memory/tests/unit/conftest.py
roampal/backend/modules/memory/tests/unit/test_context_service.py
roampal/backend/modules/memory/tests/unit/test_embedding_service.py
roampal/backend/modules/memory/tests/unit/test_knowledge_graph_service.py
roampal/backend/modules/memory/tests/unit/test_memory_bank_service.py
roampal/backend/modules/memory/tests/unit/test_outcome_service.py
roampal/backend/modules/memory/tests/unit/test_promotion_service.py
roampal/backend/modules/memory/tests/unit/test_routing_service.py
roampal/backend/modules/memory/tests/unit/test_schema_migration.py
roampal-0.2.2.dist-info/licenses/LICENSE
roampal-0.2.2.dist-info/METADATA
roampal-0.2.2.dist-info/WHEEL
roampal-0.2.2.dist-info/entry_points.txt
roampal-0.2.2.dist-info/top_level.txt
roampal-0.2.2.dist-info/RECORD
