Metadata-Version: 2.4
Name: roampal
Version: 0.2.2
Summary: Persistent memory for AI coding tools (Claude Code, Cursor, etc.)
Author-email: Roampal <hello@roampal.ai>
License: Apache-2.0
Project-URL: Homepage, https://roampal.ai
Project-URL: Repository, https://github.com/roampal/roampal-core
Project-URL: Documentation, https://docs.roampal.ai
Keywords: ai,memory,claude,cursor,mcp,llm
Classifier: Development Status :: 4 - Beta
Classifier: Intended Audience :: Developers
Classifier: License :: OSI Approved :: Apache Software License
Classifier: Programming Language :: Python :: 3
Classifier: Programming Language :: Python :: 3.10
Classifier: Programming Language :: Python :: 3.11
Classifier: Programming Language :: Python :: 3.12
Requires-Python: >=3.10
License-File: LICENSE
Requires-Dist: chromadb<2.0.0,>=1.0.0
Requires-Dist: sentence-transformers>=2.2.0
Requires-Dist: fastapi>=0.100.0
Requires-Dist: uvicorn>=0.22.0
Requires-Dist: mcp>=1.0.0
Requires-Dist: httpx>=0.24.0
Requires-Dist: pydantic>=2.0.0
Requires-Dist: rank-bm25>=0.2.0
Requires-Dist: nltk>=3.8.0
Provides-Extra: dev
Requires-Dist: pytest>=7.0.0; extra == "dev"
Requires-Dist: pytest-asyncio>=0.21.0; extra == "dev"
Dynamic: license-file
